Workbook

Sheet Read me
A1: HydrateServe - commercial pricing model
A2: Built 27 July 2026. Moves the commercial plan from a flat $699/month to four volume bands.
B4: What this is for
B5: The decision | C5: Whether to replace the flat $699/month commercial plan with volume bands.
B6: The problem | C6: A flat fee captured 46% of the value at 25 bottles/day and 8% at 120 - the same price for delivering $9,812 and $92,076 of annual saving.
B7: The answer | C7: Four bands: up to 40/day $699, 41-70 $999, 71-100 $1,299, 101+ $1,599.
B8: Why four, not three | C8: Three bands needed $400 steps, and a venue one bottle over a boundary lost $3,963 a year in saving. Four bands cut the step to $300 and the worst cliff to $2,763, with no loss of capture.
B10: How to use it
B11: Edit the yellow cells | C11: Every yellow cell is an input. Everything else is a formula and will update on its own.
B12: Start on Tiers | C12: Change a monthly fee there and every other sheet re-prices.
B13: Then Cost to serve | C13: Line items come from HydrateServe_Financial_Planner.xlsx. The planner marks them all as estimates, so treat the margin columns as indicative until real invoices land.
B14: Servicing is outsourced | C14: No salaried tech and no van: a plumber installs and maintains, paid per job. Set the rate and visit counts at the top of Cost to serve - the rate is the biggest single lever in the model.
B15: Keep the site in step | C15: The same bands are hardcoded in commercial/index.html as the TIERS array. Change both together.
B17: Colour key
B18: Yellow fill, blue text | C18: An input. Change these.
B19: Black text | C19: A formula. Do not overwrite.
B20: Green text | C20: A link to another sheet.
B22: Assumptions, and where they came from
B23: Trading days | C23: 7 days a week, 52 weeks = 364 days. Matches the on-site calculator. A venue closed 2 days a week should have its daily volume dropped to match.
B24: Bottle size | C24: 750ml equivalent.
B25: Bought-in prices | C25: $2.00-$2.60/bottle by venue type. These are the defaults already live in the website calculator, not audited invoices.
B26: Volumes | C26: The venue presets from the website calculator. Typical figures, not customer data.
B27: Cost to serve | C27: PLACEHOLDER. Install $2,200, hardware $3,400 over 5 years, CO2 $45/mth, filters $38/mth, service $55/mth. I had no cost data - replace these.
B28: GST | C28: All figures exclude GST.
B29: Revenue/margin | C29: Gross, before staff time, glassware and washing.

Sheet Tiers
A1: Pricing tiers
A2: The only place fees are set. Change a monthly fee and the whole workbook re-prices.
A4: Tier | B4: From (bottles/day) | C4: To (bottles/day) | D4: Monthly fee | E4: Annual fee | F4: vs flat $699/yr
A5: Tier 1 | B5: 1 | C5: 40 | D5: 699 | E5: =D5*12 -> 8388 | F5: =E5-Tiers!$B$15*12 -> 0
A6: Tier 2 | B6: 41 | C6: 70 | D6: 999 | E6: =D6*12 -> 11988 | F6: =E6-Tiers!$B$15*12 -> 3600
A7: Tier 3 | B7: 71 | C7: 100 | D7: 1299 | E7: =D7*12 -> 15588 | F7: =E7-Tiers!$B$15*12 -> 7200
A8: Tier 4 | B8: 101 | C8: and above | D8: 1599 | E8: =D8*12 -> 19188 | F8: =E8-Tiers!$B$15*12 -> 10800
A10: Trading assumptions
A11: Trading days per week | B11: 7
A12: Weeks per year | B12: 52
A13: Trading days per year | B13: =B11*B12 -> 364
A15: Old flat fee (for comparison) | B15: 699
A17: Bands are matched on "From" with an approximate MATCH, so the From column must stay sorted ascending.

Sheet Venue economics
A1: What each venue profile looks like
A2: Volumes and bought-in prices are the website calculator defaults. Band fee is looked up from the Tiers sheet.
A5: Venue profile | B5: Bottles /day | C5: Bottles /year | D5: Bought in $/btl | E5: They spend now | F5: Band fee /mth | G5: Band fee /year | H5: They save | I5: We capture | J5: Flat $699 capture | K5: Their $/btl with us | L5: Their water revenue
A6: Kitchen / Office | B6: 25 | C6: =B6*Tiers!$B$13 -> 9100 | D6: 2 | E6: =C6*D6 -> 18200 | F6: =INDEX(Tiers!$D$5:$D$8,MATCH(B6,Tiers!$B$5:$B$8,1)) -> 699 | G6: =F6*12 -> 8388 | H6: =E6-G6 -> 9812 | I6: =IFERROR(G6/E6,0) -> 0.46087912 | J6: =IFERROR(Tiers!$B$15*12/E6,0) -> 0.46087912 | K6: =IFERROR(G6/C6,0) -> 0.92175824 | L6: not resold
A7: Cafe | B7: 30 | C7: =B7*Tiers!$B$13 -> 10920 | D7: 2.2 | E7: =C7*D7 -> 24024 | F7: =INDEX(Tiers!$D$5:$D$8,MATCH(B7,Tiers!$B$5:$B$8,1)) -> 699 | G7: =F7*12 -> 8388 | H7: =E7-G7 -> 15636 | I7: =IFERROR(G7/E7,0) -> 0.34915085 | J7: =IFERROR(Tiers!$B$15*12/E7,0) -> 0.34915085 | K7: =IFERROR(G7/C7,0) -> 0.76813187 | L7: 74256
A8: Bar / Club | B8: 45 | C8: =B8*Tiers!$B$13 -> 16380 | D8: 2.4 | E8: =C8*D8 -> 39312 | F8: =INDEX(Tiers!$D$5:$D$8,MATCH(B8,Tiers!$B$5:$B$8,1)) -> 999 | G8: =F8*12 -> 11988 | H8: =E8-G8 -> 27324 | I8: =IFERROR(G8/E8,0) -> 0.30494505 | J8: =IFERROR(Tiers!$B$15*12/E8,0) -> 0.21336996 | K8: =IFERROR(G8/C8,0) -> 0.73186813 | L8: 116298
A9: Restaurant | B9: 55 | C9: =B9*Tiers!$B$13 -> 20020 | D9: 2.6 | E9: =C9*D9 -> 52052 | F9: =INDEX(Tiers!$D$5:$D$8,MATCH(B9,Tiers!$B$5:$B$8,1)) -> 999 | G9: =F9*12 -> 11988 | H9: =E9-G9 -> 40064 | I9: =IFERROR(G9/E9,0) -> 0.23030815 | J9: =IFERROR(Tiers!$B$15*12/E9,0) -> 0.16114655 | K9: =IFERROR(G9/C9,0) -> 0.5988012 | L9: 144144
A10: Hotel / Function | B10: 90 | C10: =B10*Tiers!$B$13 -> 32760 | D10: 2.3 | E10: =C10*D10 -> 75348 | F10: =INDEX(Tiers!$D$5:$D$8,MATCH(B10,Tiers!$B$5:$B$8,1)) -> 1299 | G10: =F10*12 -> 15588 | H10: =E10-G10 -> 59760 | I10: =IFERROR(G10/E10,0) -> 0.20688008 | J10: =IFERROR(Tiers!$B$15*12/E10,0) -> 0.11132346 | K10: =IFERROR(G10/C10,0) -> 0.47582418 | L10: 229320
A11: Large hotel group | B11: 120 | C11: =B11*Tiers!$B$13 -> 43680 | D11: 2.3 | E11: =C11*D11 -> 100464 | F11: =INDEX(Tiers!$D$5:$D$8,MATCH(B11,Tiers!$B$5:$B$8,1)) -> 1599 | G11: =F11*12 -> 19188 | H11: =E11-G11 -> 81276 | I11: =IFERROR(G11/E11,0) -> 0.19099379 | J11: =IFERROR(Tiers!$B$15*12/E11,0) -> 0.083492594 | K11: =IFERROR(G11/C11,0) -> 0.43928571 | L11: 305760
A12: Totals / average | E12: =SUM(E6:E11) -> 309400 | G12: =SUM(G6:G11) -> 75528 | H12: =SUM(H6:H11) -> 233872 | I12: =IFERROR(G12/E12,0) -> 0.24411118 | J12: =IFERROR(Tiers!$B$15*12*6/E12,0) -> 0.16266322
A14: Read the two capture columns together: banding lifts capture at the top end without any venue ceasing to save money.

Sheet Capture curve
A1: Value capture across the volume range
A2: Why a flat fee was the wrong shape: at $2.30/bottle bought in, flat capture collapses as volume rises.
A4: Bought-in price used for this sweep | B4: 2.3
A5: Bottles /day | B5: Bottles /year | C5: They spend | D5: Flat fee /yr | E5: Flat capture | F5: Band fee /yr | G5: Band capture | H5: They save (banded) | I5: Their $/btl (banded)
A6: 10 | B6: =A6*Tiers!$B$13 -> 3640 | C6: =B6*$B$4 -> 8372 | D6: =Tiers!$B$15*12 -> 8388 | E6: =IFERROR(D6/C6,0) -> 1.0019111 | F6: =INDEX(Tiers!$D$5:$D$8,MATCH(A6,Tiers!$B$5:$B$8,1))*12 -> 8388 | G6: =IFERROR(F6/C6,0) -> 1.0019111 | H6: =C6-F6 -> -16 | I6: =IFERROR(F6/B6,0) -> 2.3043956
A7: 15 | B7: =A7*Tiers!$B$13 -> 5460 | C7: =B7*$B$4 -> 12558 | D7: =Tiers!$B$15*12 -> 8388 | E7: =IFERROR(D7/C7,0) -> 0.66794075 | F7: =INDEX(Tiers!$D$5:$D$8,MATCH(A7,Tiers!$B$5:$B$8,1))*12 -> 8388 | G7: =IFERROR(F7/C7,0) -> 0.66794075 | H7: =C7-F7 -> 4170 | I7: =IFERROR(F7/B7,0) -> 1.5362637
A8: 20 | B8: =A8*Tiers!$B$13 -> 7280 | C8: =B8*$B$4 -> 16744 | D8: =Tiers!$B$15*12 -> 8388 | E8: =IFERROR(D8/C8,0) -> 0.50095557 | F8: =INDEX(Tiers!$D$5:$D$8,MATCH(A8,Tiers!$B$5:$B$8,1))*12 -> 8388 | G8: =IFERROR(F8/C8,0) -> 0.50095557 | H8: =C8-F8 -> 8356 | I8: =IFERROR(F8/B8,0) -> 1.1521978
A9: 25 | B9: =A9*Tiers!$B$13 -> 9100 | C9: =B9*$B$4 -> 20930 | D9: =Tiers!$B$15*12 -> 8388 | E9: =IFERROR(D9/C9,0) -> 0.40076445 | F9: =INDEX(Tiers!$D$5:$D$8,MATCH(A9,Tiers!$B$5:$B$8,1))*12 -> 8388 | G9: =IFERROR(F9/C9,0) -> 0.40076445 | H9: =C9-F9 -> 12542 | I9: =IFERROR(F9/B9,0) -> 0.92175824
A10: 30 | B10: =A10*Tiers!$B$13 -> 10920 | C10: =B10*$B$4 -> 25116 | D10: =Tiers!$B$15*12 -> 8388 | E10: =IFERROR(D10/C10,0) -> 0.33397038 | F10: =INDEX(Tiers!$D$5:$D$8,MATCH(A10,Tiers!$B$5:$B$8,1))*12 -> 8388 | G10: =IFERROR(F10/C10,0) -> 0.33397038 | H10: =C10-F10 -> 16728 | I10: =IFERROR(F10/B10,0) -> 0.76813187
A11: 35 | B11: =A11*Tiers!$B$13 -> 12740 | C11: =B11*$B$4 -> 29302 | D11: =Tiers!$B$15*12 -> 8388 | E11: =IFERROR(D11/C11,0) -> 0.28626032 | F11: =INDEX(Tiers!$D$5:$D$8,MATCH(A11,Tiers!$B$5:$B$8,1))*12 -> 8388 | G11: =IFERROR(F11/C11,0) -> 0.28626032 | H11: =C11-F11 -> 20914 | I11: =IFERROR(F11/B11,0) -> 0.65839874
A12: 40 | B12: =A12*Tiers!$B$13 -> 14560 | C12: =B12*$B$4 -> 33488 | D12: =Tiers!$B$15*12 -> 8388 | E12: =IFERROR(D12/C12,0) -> 0.25047778 | F12: =INDEX(Tiers!$D$5:$D$8,MATCH(A12,Tiers!$B$5:$B$8,1))*12 -> 8388 | G12: =IFERROR(F12/C12,0) -> 0.25047778 | H12: =C12-F12 -> 25100 | I12: =IFERROR(F12/B12,0) -> 0.5760989
A13: 45 | B13: =A13*Tiers!$B$13 -> 16380 | C13: =B13*$B$4 -> 37674 | D13: =Tiers!$B$15*12 -> 8388 | E13: =IFERROR(D13/C13,0) -> 0.22264692 | F13: =INDEX(Tiers!$D$5:$D$8,MATCH(A13,Tiers!$B$5:$B$8,1))*12 -> 11988 | G13: =IFERROR(F13/C13,0) -> 0.31820354 | H13: =C13-F13 -> 25686 | I13: =IFERROR(F13/B13,0) -> 0.73186813
A14: 50 | B14: =A14*Tiers!$B$13 -> 18200 | C14: =B14*$B$4 -> 41860 | D14: =Tiers!$B$15*12 -> 8388 | E14: =IFERROR(D14/C14,0) -> 0.20038223 | F14: =INDEX(Tiers!$D$5:$D$8,MATCH(A14,Tiers!$B$5:$B$8,1))*12 -> 11988 | G14: =IFERROR(F14/C14,0) -> 0.28638318 | H14: =C14-F14 -> 29872 | I14: =IFERROR(F14/B14,0) -> 0.65868132
A15: 55 | B15: =A15*Tiers!$B$13 -> 20020 | C15: =B15*$B$4 -> 46046 | D15: =Tiers!$B$15*12 -> 8388 | E15: =IFERROR(D15/C15,0) -> 0.18216566 | F15: =INDEX(Tiers!$D$5:$D$8,MATCH(A15,Tiers!$B$5:$B$8,1))*12 -> 11988 | G15: =IFERROR(F15/C15,0) -> 0.26034835 | H15: =C15-F15 -> 34058 | I15: =IFERROR(F15/B15,0) -> 0.5988012
A16: 60 | B16: =A16*Tiers!$B$13 -> 21840 | C16: =B16*$B$4 -> 50232 | D16: =Tiers!$B$15*12 -> 8388 | E16: =IFERROR(D16/C16,0) -> 0.16698519 | F16: =INDEX(Tiers!$D$5:$D$8,MATCH(A16,Tiers!$B$5:$B$8,1))*12 -> 11988 | G16: =IFERROR(F16/C16,0) -> 0.23865265 | H16: =C16-F16 -> 38244 | I16: =IFERROR(F16/B16,0) -> 0.5489011
A17: 65 | B17: =A17*Tiers!$B$13 -> 23660 | C17: =B17*$B$4 -> 54418 | D17: =Tiers!$B$15*12 -> 8388 | E17: =IFERROR(D17/C17,0) -> 0.15414017 | F17: =INDEX(Tiers!$D$5:$D$8,MATCH(A17,Tiers!$B$5:$B$8,1))*12 -> 11988 | G17: =IFERROR(F17/C17,0) -> 0.22029476 | H17: =C17-F17 -> 42430 | I17: =IFERROR(F17/B17,0) -> 0.50667794
... A28: 120 | B28: =A28*Tiers!$B$13 -> 43680 | C28: =B28*$B$4 -> 100464 | D28: =Tiers!$B$15*12 -> 8388 | E28: =IFERROR(D28/C28,0) -> 0.083492594 | F28: =INDEX(Tiers!$D$5:$D$8,MATCH(A28,Tiers!$B$5:$B$8,1))*12 -> 19188 | G28: =IFERROR(F28/C28,0) -> 0.19099379 | H28: =C28-F28 -> 81276 | I28: =IFERROR(F28/B28,0) -> 0.43928571
A30: Flat capture falls from 33% to 8% across this range. Banded holds between 19% and 83% - a consistent share of a growing prize.
A31: Break-even (the volume below which buying it in is cheaper) at this price: 11 bottles/day on Tier 1.

Sheet Cost to serve
A1: Cost to serve
A2: Line items from HydrateServe_Financial_Planner.xlsx, re-cut for outsourced servicing - no salaried tech, no van.
A3: The planner marks every one of these as an estimate. They are better than guesses but they are not invoices - replace with actuals as they land.
A5: OUTSOURCED SERVICE (plumber, paid per job)
A6: Plumber rate per visit | B6: 180 | D6: NZ trade callout. The single biggest lever on this sheet.
A7: Scheduled visits per year | B7: 4 | D7: Filter change / sanitisation. Planner assumed quarterly.
A8: Reactive callouts per year | B8: 1 | D8: Faults and adjustments. Raise this once you have fleet data.
A9: Service labour per system, per month | B9: =(B7+B8)*B6/12 -> 75
A11: Equipment & installation - one-off per system | B11: Amount | D11: Note
A12: Sparkling/still under-counter system (carbonator + chiller) | B12: 2200 | D12: Planner - commercial unit, Eastpure/EU supplier quote to confirm
A13: Tap / font hardware | B13: 250 | D13: Planner - premium font consistent with brand positioning
A14: Filtration setup (carbon block / RO) | B14: 600 | D14: Planner - align with Hydrate Filters landed cost
A15: CO2 cylinder, regulator & lines | B15: 300 | D15: Planner - Eziswap / BOC setup
A16: Installation labour | B16: 1000 | D16: Planner - plumber/tech half-day
A17: Total capex per system | B17: =SUM(B12:B16) -> 4350
A19: Servicing & consumables - per system, per month | B19: Amount | C19: Scales with volume? | D19: Note
A20: CO2 swaps | B20: 120 | C20: Yes | D20: Planner - ~1 Eziswap 6kg swap/month at the baseline volume
A21: Filter replacements (amortised) | B21: 25 | C21: Yes | D21: Planner - cartridge cost spread across change interval
A22: Consumables (bottles, caps, sanitiser) | B22: 30 | C22: Yes | D22: Planner - glass breakage/replacement included
A23: Outsourced service labour | B23: =B9 -> 75 | C23: No | D23: Plumber, from the block above. Per site, not per bottle
A24: Parts & warranty provision | B24: 15 | C24: No | D24: Planner - refine with fleet data
A25: Subtotal - scales with volume | B25: =SUMIF(C20:C24,"Yes",B20:B24) -> 175 | D25: CO2, filters and consumables all track how much water goes out.
A26: Subtotal - fixed per site | B26: =SUMIF(C20:C24,"No",B20:B24) -> 90
A27: Total at the baseline volume | B27: =B25+B26 -> 265
A29: Baseline volume those figures assume (bottles/day) | B29: 30 | D29: The cafe preset. Cost at any other volume scales the variable subtotal from here.
A31: OVERHEADS
A32: Base monthly overheads (admin, software, insurance) | B32: 1500 | D32: Fixed regardless of fleet size.
A33: No van and no service-tech salary: installation and maintenance are outsourced to a plumber and priced per job above. That removes the 80-systems-per-tech capacity step, so profit grows smoothly instead of dropping at every hire.
A35: Margin by band (at the top of each band - worst case) | B35: Fee /month | C35: Bottles /day | D35: Servicing /month | E35: Gross margin | F35: Margin % | G35: Payback (months)
A36: Tier 1 (1-40/day) | B36: =Tiers!D5 -> 699 | C36: 40 | D36: =$B$26+$B$25*(C36/$B$29) -> 323.33333 | E36: =B36-D36 -> 375.66667 | F36: =IFERROR(E36/B36,0) -> 0.53743443 | G36: =IFERROR($B$17/E36,0) -> 11.579414
A37: Tier 2 (41-70/day) | B37: =Tiers!D6 -> 999 | C37: 70 | D37: =$B$26+$B$25*(C37/$B$29) -> 498.33333 | E37: =B37-D37 -> 500.66667 | F37: =IFERROR(E37/B37,0) -> 0.50116783 | G37: =IFERROR($B$17/E37,0) -> 8.6884154
A38: Tier 3 (71-100/day) | B38: =Tiers!D7 -> 1299 | C38: 100 | D38: =$B$26+$B$25*(C38/$B$29) -> 673.33333 | E38: =B38-D38 -> 625.66667 | F38: =IFERROR(E38/B38,0) -> 0.48165255 | G38: =IFERROR($B$17/E38,0) -> 6.9525839
A39: Tier 4 (101+/day) | B39: =Tiers!D8 -> 1599 | C39: 120 | D39: =$B$26+$B$25*(C39/$B$29) -> 790 | E39: =B39-D39 -> 809 | F39: =IFERROR(E39/B39,0) -> 0.50594121 | G39: =IFERROR($B$17/E39,0) -> 5.3770087
A41: The top band is open-ended, so its margin keeps falling as volume climbs: at the current numbers Tier 4 stops paying at about 259 bottles/day. Either cap it or add a per-bottle charge above ~200/day.

Sheet Revenue model
A1: What a book of business looks like
A2: Change the customer counts in yellow. Servicing is costed at each band’s mid-volume, not a flat average.
A5: Tier | B5: Customers | C5: Fee /month | D5: Mid volume | E5: Servicing /system | F5: Contribution /mth | G5: Capex to install
A6: Tier 1 (1-40/day) | B6: 12 | C6: =Tiers!D5 -> 699 | D6: 21 | E6: ='Cost to serve'!$B$26+'Cost to serve'!$B$25*(D6/'Cost to serve'!$B$29) -> 212.5 | F6: =B6*(C6-E6) -> 5838 | G6: =B6*'Cost to serve'!$B$17 -> 52200
A7: Tier 2 (41-70/day) | B7: 6 | C7: =Tiers!D6 -> 999 | D7: 56 | E7: ='Cost to serve'!$B$26+'Cost to serve'!$B$25*(D7/'Cost to serve'!$B$29) -> 416.66667 | F7: =B7*(C7-E7) -> 3494 | G7: =B7*'Cost to serve'!$B$17 -> 26100
A8: Tier 3 (71-100/day) | B8: 3 | C8: =Tiers!D7 -> 1299 | D8: 86 | E8: ='Cost to serve'!$B$26+'Cost to serve'!$B$25*(D8/'Cost to serve'!$B$29) -> 591.66667 | F8: =B8*(C8-E8) -> 2122 | G8: =B8*'Cost to serve'!$B$17 -> 13050
A9: Tier 4 (101+/day) | B9: 1 | C9: =Tiers!D8 -> 1599 | D9: 111 | E9: ='Cost to serve'!$B$26+'Cost to serve'!$B$25*(D9/'Cost to serve'!$B$29) -> 737.5 | F9: =B9*(C9-E9) -> 861.5 | G9: =B9*'Cost to serve'!$B$17 -> 4350
A10: Total | B10: =SUM(B6:B9) -> 22 | F10: =SUM(F6:F9) -> 12315.5 | G10: =SUM(G6:G9) -> 95700
A12: Contribution after servicing | B12: =F10 -> 12315.5
A13: Less fixed overheads | B13: =-'Cost to serve'!$B$32 -> -1500
A14: Net operating profit / month | B14: =B12+B13 -> 10815.5
A15: Net operating profit / year | B15: =B14*12 -> 129786
A16: Break-even fleet size (systems) | B16: =ROUNDUP('Cost to serve'!$B$32/(F10/B10),0) -> 3
A18: Against the old flat fee
A19: Revenue /year, flat $699 | B19: =B10*Tiers!$B$15*12 -> 184536
A20: Revenue /year, banded | B20: =SUMPRODUCT(B6:B9,C6:C9)*12 -> 238536
A21: Difference | B21: =B20-B19 -> 54000
A23: Customer counts are an illustrative mix (12 / 6 / 3 / 1), not a forecast. Change them to your pipeline.
A24: Capex is the cash needed to put those systems in, not a monthly cost - payback per system is on the Cost to serve sheet.
